chia/__init__.py
chia/version.py
chia/components/__init__.py
chia/components/base_models/__init__.py
chia/components/base_models/incremental_model.py
chia/components/base_models/keras/__init__.py
chia/components/base_models/keras/keras_basemodel.py
chia/components/base_models/keras/keras_dataaugmentation.py
chia/components/base_models/keras/keras_featureextractor.py
chia/components/base_models/keras/keras_learningrateschedule.py
chia/components/base_models/keras/keras_preprocessor.py
chia/components/base_models/keras/keras_trainer.py
chia/components/classifiers/__init__.py
chia/components/classifiers/keras_chillax_hc.py
chia/components/classifiers/keras_hierarchicalclassification.py
chia/components/classifiers/keras_idk_hc.py
chia/components/classifiers/keras_labelsharing_hc.py
chia/components/classifiers/keras_onehot_hc.py
chia/components/datasets/__init__.py
chia/components/datasets/core50_dataset.py
chia/components/datasets/cub2002011_dataset.py
chia/components/datasets/dataset.py
chia/components/datasets/icifar_dataset.py
chia/components/datasets/icubworld28_dataset.py
chia/components/datasets/ilsvrc2012_dataset.py
chia/components/datasets/inaturalist2018_dataset.py
chia/components/datasets/json_dataset.py
chia/components/datasets/lndw_dataset.py
chia/components/datasets/nabirds_dataset.py
chia/components/evaluators/__init__.py
chia/components/evaluators/accuracy.py
chia/components/evaluators/evaluator.py
chia/components/evaluators/hierarchical.py
chia/components/evaluators/topk_accuracy.py
chia/components/extrapolators/__init__.py
chia/components/extrapolators/adaptive.py
chia/components/extrapolators/extrapolator.py
chia/components/extrapolators/fixed.py
chia/components/interactors/__init__.py
chia/components/interactors/interactor.py
chia/components/interactors/noisy_oracle.py
chia/components/interactors/oracle.py
chia/components/runners/__init__.py
chia/components/runners/epoch.py
chia/components/runners/runner.py
chia-2.5.0.dist-info/LICENSE
chia-2.5.0.dist-info/METADATA
chia-2.5.0.dist-info/WHEEL
chia-2.5.0.dist-info/top_level.txt
chia-2.5.0.dist-info/RECORD
