Metadata-Version: 2.1
Name: chia
Version: 2.5.0
Summary: Concept Hierarchies for Incremental and Active Learning
Home-page: https://github.com/cabrust/chia
Author: Clemens-Alexander Brust
Author-email: clemens-alexander.brust@dlr.de
License: UNKNOWN
Platform: UNKNOWN
Classifier: License :: OSI Approved :: BSD License
Classifier: Programming Language :: Python :: 3.7
Classifier: Programming Language :: Python :: 3.8
Classifier: Programming Language :: Python :: 3.9
Classifier: Development Status :: 5 - Production/Stable
Classifier: Environment :: GPU
Classifier: Operating System :: POSIX :: Linux
Classifier: Topic :: Scientific/Engineering :: Artificial Intelligence
Requires-Python: >=3.7
License-File: LICENSE
Requires-Dist: python-configuration (==0.7.1)
Requires-Dist: nltk (~=3.5.0)
Requires-Dist: imageio (~=2.6)
Requires-Dist: pillow (~=8.0)
Requires-Dist: gputil (~=1.4.0)
Requires-Dist: networkx (~=2.4)
Requires-Dist: numpy (~=1.19.2)
Requires-Dist: tensorflow-addons (==0.14.0)
Requires-Dist: tensorflow (~=2.6.0)
